[TOC]

### 内部类

#### 基础

在一个类内部定义的类即为内部类. 内部类可以分为四类: **普通内部类, 静态内部类, 匿名内部类, 局部内部类**. 

只有内部类可以是 **private** 私有类, 或者 **static** 静态类. 

内部类是一种**编译器**现象, 与虚拟机无关. **编译器**将会把内部类翻译成用 **$** 分隔外部类名与内部类名的**常规类文件**, 而虚拟机则对此一无所知. 因为每个内部类都会被编译为一个**独立**的类. 

> **为什么要使用内部类?**

使用内部类最吸引人的原因是: 每个内部类都能独立地继承一个(接口的)实现, 所以无论外围类是否已经继承了某个(接口的)实现, 对于内部类都没有影响. ---《Think in java》

对于多重继承, 接口只是解决了部分问题, 而内部类使得**多重继承**的解决方案变得更加**完整**, 它能较好的解决**多重继承**问题. 

#### 普通内部类

##### 1.概述

在一个类里面直接定义一个类, 例如: 

```java
public class InnerClassTest {
    class NormalInnerClass{  
    }
}
```

这里 NormalInnerClass 类即为 InnerClassTest 类的**普通内部类**. 这种定义方式下, **普通内部类对象依赖外部类对象**而存在, 即当创建一个普通内部类对象时**需要先创建其外部类对象**. 

即创建 InnerClassA 对象时要先创建 InnerClassTest 对象, 例: 

```java
public class InnerClassTest {

    public int outField1 = 1;
    protected int outField2 = 2;
    int outField3 = 3;
    private int outField4 = 4;

    public InnerClassTest() {
        // 在外部类对象内部, 直接通过 new InnerClass(); 创建内部类对象
        InnerClassA innerObj = new InnerClassA();
        System.out.println("创建 " + this.getClass().getSimpleName() + " 对象");
        System.out.println("其内部类的 field1 字段的值为: " + innerObj.field1);
        System.out.println("其内部类的 field2 字段的值为: " + innerObj.field2);
        System.out.println("其内部类的 field3 字段的值为: " + innerObj.field3);
        System.out.println("其内部类的 field4 字段的值为: " + innerObj.field4);
    }

    public class InnerClassA {
        public int field1 = 5;
        protected int field2 = 6;
        int field3 = 7;
        private int field4 = 8;
        // static int field5 = 5; // 编译错误!普通内部类中不能定义静态属性

        public InnerClassA() {
            System.out.println("创建 " + this.getClass().getSimpleName() + " 对象");
            System.out.println("其外部类的 outField1 字段的值为: " + outField1);
            System.out.println("其外部类的 outField2 字段的值为: " + outField2);
            System.out.println("其外部类的 outField3 字段的值为: " + outField3);
            System.out.println("其外部类的 outField4 字段的值为: " + outField4);
        }
    }

    public static void main(String[] args) {
        InnerClassTest outerObj = new InnerClassTest();
        // 不在外部类内部, 使用 "外部类对象.new 内部类构造器()" 的方式创建内部类对象
        InnerClassA innerObj = outerObj.new InnerClassA();
    }
}
```

```java
创建 InnerClassA 对象
其外部类的 outField1 字段的值为: 1
其外部类的 outField2 字段的值为: 2
其外部类的 outField3 字段的值为: 3
其外部类的 outField4 字段的值为: 4
创建 InnerClassTest 对象
其内部类的 field1 字段的值为: 5
其内部类的 field2 字段的值为: 6
其内部类的 field3 字段的值为: 7
其内部类的 field4 字段的值为: 8
```

##### 2.内外访问

普通内部类就像外部类声明的一个==**普通属性字段**==一样, 因此其对象是**依附**于外部类对象而存在的. 使用一个字段肯定得**先有对象**, 使用普通内部类也要先创建外部类对象, 道理类似. 

**内部类对象**可以访问**外部类对象中所有访问权限的字段**, 外部类对象也可以通过**内部类的对象引用**来访问内部类中定义的**所有**访问权限的字段(当成普通属性字段理解即可). 

普通内部类中不能存在 static 方法, 但可以存在 static 属性, 但必须使用 final 关键字修饰. 

#### 静态内部类

##### 1.概述

静态内部类即含有 **static** 修饰的内部类, 静态内部类可以有**静态属性和方法**. **只有内部类**可以声明为 **static**. 

一个类的**静态成员**独立于这个类的**任何一个对象**存在, 只要在具有访问权限的地方, 就可以通过 "**类名.静态成员名**" 的形式来访问这个静态成员, 类似的, **静态内部类**也可以理解为一个外部类的**==静态成员==**, **创建一个类的静态内部类对象不需要依赖其外部类对象**. 

创建静态内部类实例的方式: 

- 在**外部类**中创建: 

```java
StaticClass staticClass = new StaticClass();
```

- 在**其他类**中创建, 类似于通过**类名引用静态字段**, 静态内部类就像外部类的**一个静态成员**一样, 创建其对象**无需依赖外部类对象**: 

```java
外部类名.内部类名 name = new 外部类名.内部类名();
InnerClassTest2.StaticClass staticClass = new InnerClassTest2.StaticClass();
```

例如: 

```java
public class InnerClassTest2 {

    // 外部类实例字段
    public int outerField = 1;

    public static int outerStaticField = 3;

    public InnerClassTest2() {
        System.out.println("创建 " + this.getClass().getSimpleName() + " 对象");
        // 创建静态内部类对象
        StaticClass innerObj = new StaticClass();
        System.out.println("其内部类的 field1 字段的值为: " + innerObj.field1);
        System.out.println("其内部类的 field2 字段的值为: " + innerObj.field2);
        System.out.println("其内部类的 field3 字段的值为: " + innerObj.field3);
        System.out.println("其内部类的 field4 字段的值为: " + innerObj.field4);
        System.out.println("内部类静态字段值: " + StaticClass.field5);
    }

    static class StaticClass {
        // 静态内部类中可以定义各种属性
        public int field1 = 1;
        protected int field2 = 2;
        int field3 = 3;
        private int field4 = 4;
        // 静态内部类中可以定义static属性
        static int field5 = 5;

        public StaticClass() {
            System.out.println("创建 " + StaticClass.class.getSimpleName() + " 对象");
            // 可以引用外部类的静态字段
            System.out.println("外部类静态字段值: " + InnerClassTest2.outerStaticField);
            // 不能引用外部类的普通实例字段
            // System.out.println("其外部类的 field1 字段的值为: " + outerField); // 编译错误!!
        }
    }

    public static void main(String[] args) {
        // 无需依赖外部类对象, 直接创建内部类对象
        // InnerClassTest.StaticClass staticClassObj = new InnerClassTest.StaticClass();
        InnerClassTest2 outerObj = new InnerClassTest2();
    }
}
```

```java
创建 InnerClassTest2 对象
创建 StaticClass 对象
外部类静态字段值: 3
其内部类的 field1 字段的值为: 1
其内部类的 field2 字段的值为: 2
其内部类的 field3 字段的值为: 3
其内部类的 field4 字段的值为: 4
内部类静态字段值: 5
```

##### 2.内外访问

可以把**静态内部类当做外部类的一个==静态成员属性==**. 

静态内部类中**无法访问外部类的非静态成员**, 因为外部类的非静态成员是属于**每一个外部类对象的**, 而静态内部类就是**独立**外部类对象存在的, 所以静态内部类不能访问外部类的非静态成员. 但是静态内部类**可以访问**外部类的**静态属性**. **静态属性可以互相访问**. 

而**外部类**依然可以访问静态内部类对象的**所有有访问权限**的属性, 这与普通内部类无异. 

#### 匿名内部类

##### 1.概述

匿名内部类有多种形式, 其中最常见的莫过于在**方法参数中新建一个接口对象 / 类对象**. 匿名内部类的实例如下. 

```java
// 在方法中定义匿名内部类
public void start(int interval, boolean beep){
    // 创建一个实现ActionListener接口的类对象, 需要实现的方法actionPerformed()在括号内实现
    ActionListener listener = new ActionListener(){
        @Override
        public void actionPerformed(ActionEvent event){
            System.out.println("At the tone, the time is " + new Date());
        }
    };
    Timer t = new Timer(interval, listener);
    t.start();
}
```

直接 new 一个**接口**, 并实现这个接口**声明的方法**, 在这个过程其实会创建一个**匿名内部类实现这个接口**, 并覆写接口方法. 

如果**构造参数的闭小括号后面跟一个开大括号**, 这里定义的就是匿名内部类. 

```java
Person count = new Person("Dracula") {...}
// an object of an inner class extending Person
```

匿名内部类多用于实现**回调**接口, 习惯的做法是用其实现事件监听器和其他回调. 而如今最好使用 **lambda** 表达式. 

##### 2.内外访问

**在匿名内部类中可以使用外部类的属性**, 但是外部类却**不能**使用匿名内部类中定义的属性, 因为是**匿名**内部类, 因此在外部类中无法获取这个类的类名, 也就无法得到内部类的属性信息. 

#### 局部内部类

局部内部类使用的**比较少**, 它声明在一个方法体或一段代码块的内部, 而且不在定义类的定义域之内便无法使用, 其提供的功能使用匿名内部类都可以实现, 而本身匿名内部类可以写得比它更简洁, 因此用的比较少(不给例子了). 

局部内部类**不能用 public 或 private 修饰符**进行声明. 

在局部内部类里面**可以访问外部类对象的所有访问权限(包括 private)的字段**, 而外部类却**不能访问局部内部类**中定义的字段, 因为局部内部类的定义只在其特定的**方法体或代码块**中有效, 一旦出了这个**定义域**, 那么其定义就**失效**了. 外部类不能获取局部内部类的对象, 因而无法访问局部内部类的字段. 

局部内部类有一个优点. 它们**不仅能够访问包含它们的外部类**, 还**可以访问==局部变量==**. 不过那些局部变量**必须**事实上为 ==**final**==. 如果需要变值的话一个替代方案可以是使用**长度为 1 的数组**. 数组引用为 final 但是其值可以变化. 即局部内部类只能访问**方法**中声明的 **final 类型**的变量. 

#### 内部类原理解析

##### 1.普通内部类

前面分析已知**普通内部类**可以**访问外部类所有有访问权限的字段**(包括 private 的属性), 同时外部类也可以访问普通内部类的所有有访问权限的字段. 然而理论上 **private** 字段只在被**当前类可见**. 由于外部类可以知道内部类的类型信息, 所以外部类可以访问内部类的各种属性, 但是普通内部类是**如何**能调用外部类的私有属性?

**其实==内部类持有外部类的一个引用==, 在==内部类构造函数==中会将外部类的引用传递进来, 通过这个引用即可访问外部类的 private 属性.**

这里编译一波康康. 以**普通内部类**举例: 

```java
public class InnerClassTest {

    int field1 = 1;
    private int field2 = 2;

    public InnerClassTest() {
        InnerClassA inner = new InnerClassA();
        int v = inner.x2;
    }

    public class InnerClassA {
        int x1 = field1;
        private int x2 = field2;
    }
}
```

首先用 **"javac"** 命令**编译**这个文件

```sh
$ javac InnerClassTest.java
```

编译后会得到**两个 .class 文件**: 

```java
InnerClassTest.class
InnerClassTest$InnerClassA.class
```

可见内部类编译之后是两个**独立**的 class 文件. 

再用 **"javap -c"** 命令分别**反编译**这两个 .class 文件. 

```sh
$ javap -c InnerClassTest 
$ javap -c InnerClassTest$InnerClassA
```

反编译得到 **InnerClassTest.class** 的字节码如下: 

```java
public class javase.innerclass.InnerClassTest {
    // 外部类的字段
    int field1;

    public javase.innerclass.InnerClassTest();
    Code:
    0: aload_0
    1: invokespecial #1                  // Method java/lang/Object."<init>":()V
    4: aload_0
    5: iconst_1
    6: putfield      #2                  // Field field1:I
    9: aload_0
    10: iconst_2
    11: putfield      #3                  // Field field2:I
    14: new           #4                  // class javase/innerclass/InnerClassTest$InnerClassA
    17: dup
    18: aload_0
    19: invokespecial #5                  // Method javase/innerclass/InnerClassTest$InnerClassA."<init>":(Ljavase/innerclass/InnerClassTest;)V
    22: astore_1
    23: aload_1
    24: getfield      #6                  // Field javase/innerclass/InnerClassTest$InnerClassA.x2:I
    27: istore_2
    28: return
}
```

**InnerClassTest$InnerClassA** 类的字节码如下: 

```java
public class javase.innerclass.InnerClassTest$InnerClassA {
    // 内部类的字段 
    int x1;
	// 注意: 这是对外部类对象的一个引用, 这个引用是通过构造方法传入的
    final javase.innerclass.InnerClassTest this$0;

    public javase.innerclass.InnerClassTest$InnerClassA(javase.innerclass.InnerClassTest);
    Code:
    0: aload_0
    1: aload_1
    2: putfield      #1                  // Field this$0:Ljavase/innerclass/InnerClassTest;
    5: aload_0
    6: invokespecial #2                  // Method java/lang/Object."<init>":()V
    9: aload_0
    10: aload_0
    11: getfield      #1                  // Field this$0:Ljavase/innerclass/InnerClassTest;
    14: getfield      #3                  // Field javase/innerclass/InnerClassTest.field1:I
    17: putfield      #4                  // Field x1:I
    20: aload_0
    21: aload_0
    22: getfield      #1                  // Field this$0:Ljavase/innerclass/InnerClassTest;
    25: getfield      #5                  // Field javase/innerclass/InnerClassTest.field2:I
    28: putfield      #6                  // Field x2:I
    31: return
}
```

注意上面有一个字段为: 

```java
final javase.innerclass.InnerClassTest this$0;
```

可知**编译器**给内部类提供了一个接受 InnerClassTest 类型对象(即外部类对象)的**构造方法**, 内部类本身还定义了一个名为 **this$0** 的 InnerClassTest 类型的**引用**, 这个引用在构造方法中指向了**参数所对应的外部类对象**. 所以内部类是持有外部类对象的**引用**的, 因此内部类可以通过该引用使用外部类的 **private 字段**. 

##### 2.其他内部类

上面是对**普通内部类**的分析, 但其实**匿名内部类和局部内部类的原理和普通内部类类似**, 只是在访问上有些不同: 外部类**无法**访问匿名内部类和局部内部类对象的字段, 因为外部类根本就**不知道**匿名内部类或局部内部类的**类型信息(**匿名内部类的类名被隐匿, 局部内部类只能在定义域内使用). 但匿名内部类和局部内部类却可以访问外部类的私有成员, **原理也是**通过**持有外部类对象引用**可以得到对应外部类对象的私有成员的值. 

对于**静态内部类**来说, 因为它**独立于**外部类对象而存在, 因此编译器**不会**为静态内部类对象提供外部类对象的**引用**, 因为静态内部类对象的创建根本不需要外部类对象支持. 但是**外部类对象**还是可以访问静态内部类对象的**私有成员**, **因为外部类可以知道静态内部类的类型信息**, 即可以得到静态内部类的对象, 那么就可以通过静态内部类来获得对应的私有属性值.

==**总结**:==

**普通内部类**可以与外部类**互相访问其属性**, 原理即外部类知道内部类的**类型信息**, 所以外部类可以访问内部类的类型信息; 反过来内部类是通过编译后**持有外部类对象的引用**所以可以访问外部类的各种字段. 

类似的, **匿名内部类和局部内部类**都持有外部类对象的引用, 所以可以访问外部类非静态字段, 然而外部类**不知道**匿名内部类和局部内部类的类型信息, 所以外部类不能访问其字段. 

总之, **非静态内部类(普通、匿名、局部)中都会持有对外部类的对象的引用, 从而可以访问外部类对象. 反过来就要看外部类是否知道内部类的类型信息了**. 

**静态内部类**是不依赖于任何实例对象的, 所以静态内部类**不会持有外部类的实例对象**, 所以**无法访问**外部类的非静态字段, 因此静态内部类只能访问外部类的静态字段, 而外部类是可以得到静态内部类的类型信息, 所以外部类可以访问静态内部类的各种属性. 

**静态内部类对象不依赖其外部类对象存在, 而其余的内部类对象必须依赖其外部类对象而存在**. 

#### 开发建议

如果内部类访问了 **private** 私有数据域, 就有可能通过**附加在外围类所在包**中的其他类**访问**它们, 这就存在一定的**安全问题**. 但这需要将攻击代码与被攻击类放在**同一个包**中. 



#### 参考资料

- https://blog.csdn.net/hacker_zhidian/article/details/82193100
- 《Java 核心技术卷》









